{
  "sampleProducts": [
    {
      "id": 6,
      "userId": 400,
      "name": "Kumar"
    },
    {
      "id": 7,
      "userId": 5000,
      "name": "Kumar"
    },
    {
      "id": 8,
      "userId": 4354351,
      "name": "543543"
    },
    {
      "id": 9,
      "userId": 24325,
      "name": "Krishaan"
    }
  ],
  "Assessment_Details": [
    {
      "title": "title-1",
      "skill-tags": [
        {
          "name": "java",
          "namee": "javascript"
        }
      ],
      "description": "description"
    }
  ]
}